hyperspell/__init__.py
hyperspell/_base_client.py
hyperspell/_client.py
hyperspell/_compat.py
hyperspell/_constants.py
hyperspell/_exceptions.py
hyperspell/_files.py
hyperspell/_models.py
hyperspell/_qs.py
hyperspell/_resource.py
hyperspell/_response.py
hyperspell/_streaming.py
hyperspell/_types.py
hyperspell/_version.py
hyperspell/pagination.py
hyperspell/py.typed
hyperspell/_utils/__init__.py
hyperspell/_utils/_logs.py
hyperspell/_utils/_proxy.py
hyperspell/_utils/_reflection.py
hyperspell/_utils/_streams.py
hyperspell/_utils/_sync.py
hyperspell/_utils/_transform.py
hyperspell/_utils/_typing.py
hyperspell/_utils/_utils.py
hyperspell/lib/.keep
hyperspell/resources/__init__.py
hyperspell/resources/auth.py
hyperspell/resources/collections.py
hyperspell/resources/documents.py
hyperspell/resources/query.py
hyperspell/types/__init__.py
hyperspell/types/auth_user_token_params.py
hyperspell/types/collection.py
hyperspell/types/collection_create_params.py
hyperspell/types/collection_list_params.py
hyperspell/types/collection_list_response.py
hyperspell/types/document.py
hyperspell/types/document_add_params.py
hyperspell/types/document_add_url_params.py
hyperspell/types/document_list_params.py
hyperspell/types/document_list_response.py
hyperspell/types/document_status.py
hyperspell/types/document_upload_params.py
hyperspell/types/query_search_params.py
hyperspell/types/query_search_response.py
hyperspell/types/token.py
hyperspell-1.0.0.dist-info/METADATA
hyperspell-1.0.0.dist-info/WHEEL
hyperspell-1.0.0.dist-info/licenses/LICENSE
hyperspell-1.0.0.dist-info/RECORD
